{
    "sunnys": {
        "rank": 1555,
        "minutes_streamed": 8753,
        "avg_viewers": 1092,
        "max_viewers": 6653,
        "hours_watched": 159371,
        "followers": 4077,
        "followers_total": 128158
    },
    "santipulgaz": {
        "rank": 931,
        "minutes_streamed": 11048,
        "avg_viewers": 1477,
        "max_viewers": 11327,
        "hours_watched": 272018,
        "followers": 4332,
        "followers_total": 73201
    },
    "youngbasedgo": {
        "rank": 2585,
        "minutes_streamed": 19077,
        "avg_viewers": 421,
        "max_viewers": 8881,
        "hours_watched": 133737,
        "followers": 1449,
        "followers_total": 67924
    },
    "arky": {
        "rank": 166,
        "minutes_streamed": 15161,
        "avg_viewers": 5088,
        "max_viewers": 32153,
        "hours_watched": 1285555,
        "followers": 15773,
        "followers_total": 465346
    },
    "yugi2x": {
        "rank": 189,
        "minutes_streamed": 18367,
        "avg_viewers": 3999,
        "max_viewers": 16859,
        "hours_watched": 1224207,
        "followers": 12063,
        "followers_total": 305609
    },
    "nosiiree": {
        "rank": 5345,
        "minutes_streamed": 9257,
        "avg_viewers": 328,
        "max_viewers": 1962,
        "hours_watched": 50556,
        "followers": 843,
        "followers_total": 67448
    },
    "1jdab1": {
        "rank": 6786,
        "minutes_streamed": 8684,
        "avg_viewers": 267,
        "max_viewers": 1442,
        "hours_watched": 38574,
        "followers": 1310,
        "followers_total": 33746
    },
    "redify": {
        "rank": 10318,
        "minutes_streamed": 9317,
        "avg_viewers": 164,
        "max_viewers": 2057,
        "hours_watched": 25399,
        "followers": 634,
        "followers_total": 48281
    },
    "bigmonraph": {
        "rank": 2909,
        "minutes_streamed": 7869,
        "avg_viewers": 667,
        "max_viewers": 3612,
        "hours_watched": 87423,
        "followers": 3340,
        "followers_total": 36500
    }
}