{
    "sunnys": {
        "rank": 1376,
        "minutes_streamed": 10661,
        "avg_viewers": 998,
        "max_viewers": 4546,
        "hours_watched": 177403,
        "followers": 4861,
        "followers_total": 125699
    },
    "santipulgaz": {
        "rank": 1042,
        "minutes_streamed": 10983,
        "avg_viewers": 1235,
        "max_viewers": 7884,
        "hours_watched": 226053,
        "followers": 9545,
        "followers_total": 70373
    },
    "youngbasedgo": {
        "rank": 1084,
        "minutes_streamed": 33160,
        "avg_viewers": 469,
        "max_viewers": 8881,
        "hours_watched": 259430,
        "followers": 1759,
        "followers_total": 67424
    },
    "arky": {
        "rank": 160,
        "minutes_streamed": 14420,
        "avg_viewers": 4863,
        "max_viewers": 16928,
        "hours_watched": 1168791,
        "followers": 11547,
        "followers_total": 453785
    },
    "yugi2x": {
        "rank": 173,
        "minutes_streamed": 17222,
        "avg_viewers": 3988,
        "max_viewers": 16671,
        "hours_watched": 1144589,
        "followers": 10995,
        "followers_total": 297243
    },
    "nosiiree": {
        "rank": 4944,
        "minutes_streamed": 8859,
        "avg_viewers": 336,
        "max_viewers": 2438,
        "hours_watched": 49667,
        "followers": 925,
        "followers_total": 67056
    },
    "1jdab1": {
        "rank": 4540,
        "minutes_streamed": 7173,
        "avg_viewers": 425,
        "max_viewers": 4386,
        "hours_watched": 50829,
        "followers": 2462,
        "followers_total": 33030
    },
    "redify": {
        "rank": 7785,
        "minutes_streamed": 10786,
        "avg_viewers": 182,
        "max_viewers": 1769,
        "hours_watched": 32709,
        "followers": 754,
        "followers_total": 47985
    },
    "bigmonraph": {
        "rank": 4036,
        "minutes_streamed": 5515,
        "avg_viewers": 566,
        "max_viewers": 3893,
        "hours_watched": 51988,
        "followers": 2348,
        "followers_total": 33956
    }
}