{
    "sunnys": {
        "rank": 1185,
        "minutes_streamed": 13051,
        "avg_viewers": 1053,
        "max_viewers": 3110,
        "hours_watched": 228990,
        "followers": 4972,
        "followers_total": 124487
    },
    "santipulgaz": {
        "rank": 1128,
        "minutes_streamed": 10924,
        "avg_viewers": 1247,
        "max_viewers": 7884,
        "hours_watched": 226983,
        "followers": 9263,
        "followers_total": 69053
    },
    "youngbasedgo": {
        "rank": 1078,
        "minutes_streamed": 35902,
        "avg_viewers": 500,
        "max_viewers": 2891,
        "hours_watched": 299204,
        "followers": 1949,
        "followers_total": 66666
    },
    "arky": {
        "rank": 193,
        "minutes_streamed": 14357,
        "avg_viewers": 4701,
        "max_viewers": 16928,
        "hours_watched": 1124818,
        "followers": 11174,
        "followers_total": 451791
    },
    "yugi2x": {
        "rank": 208,
        "minutes_streamed": 17025,
        "avg_viewers": 3862,
        "max_viewers": 16671,
        "hours_watched": 1095932,
        "followers": 10168,
        "followers_total": 294781
    },
    "nosiiree": {
        "rank": 5473,
        "minutes_streamed": 7245,
        "avg_viewers": 373,
        "max_viewers": 2438,
        "hours_watched": 45028,
        "followers": 656,
        "followers_total": 66671
    },
    "1jdab1": {
        "rank": 3312,
        "minutes_streamed": 7267,
        "avg_viewers": 625,
        "max_viewers": 5641,
        "hours_watched": 75679,
        "followers": 2568,
        "followers_total": 32516
    },
    "redify": {
        "rank": 6428,
        "minutes_streamed": 11511,
        "avg_viewers": 234,
        "max_viewers": 1769,
        "hours_watched": 44798,
        "followers": 720,
        "followers_total": 47796
    },
    "bigmonraph": {
        "rank": 2801,
        "minutes_streamed": 4990,
        "avg_viewers": 906,
        "max_viewers": 7564,
        "hours_watched": 75376,
        "followers": 7001,
        "followers_total": 33345
    }
}